PyFloatplane/__init__.py
PyFloatplane/annotations.py
PyFloatplane/client.py
PyFloatplane/config.py
PyFloatplane/models/Activity.py
PyFloatplane/models/Client.py
PyFloatplane/models/Comment.py
PyFloatplane/models/CommentInteraction.py
PyFloatplane/models/Creator.py
PyFloatplane/models/Edge.py
PyFloatplane/models/EdgeDatacenter.py
PyFloatplane/models/EdgeServer.py
PyFloatplane/models/Error.py
PyFloatplane/models/Firebase.py
PyFloatplane/models/FloatplaneInfo.py
PyFloatplane/models/FullImage.py
PyFloatplane/models/Image.py
PyFloatplane/models/Plan.py
PyFloatplane/models/Playlist.py
PyFloatplane/models/Subscription.py
PyFloatplane/models/User.py
PyFloatplane/models/UserConnection.py
PyFloatplane/models/Video.py
PyFloatplane/models/__init__.py
pyFloatplane-1.1.3.dist-info/DESCRIPTION.rst
pyFloatplane-1.1.3.dist-info/METADATA
pyFloatplane-1.1.3.dist-info/RECORD
pyFloatplane-1.1.3.dist-info/WHEEL
pyFloatplane-1.1.3.dist-info/metadata.json
pyFloatplane-1.1.3.dist-info/top_level.txt
