Metadata-Version: 2.0
Name: pyFloatplane
Version: 1.1.3
Summary: Unofficial REST-Client bindings for Floatplane.com
Home-page: https://git.dark-it.net/stappert/pyFloatpane
Author: Sammy8806
Author-email: mail@sammy8806.de
License: MIT
Keywords: floatplane floatplanemedia rest-client linustechtips linusmedia videos
Platform: UNKNOWN
Classifier: Development Status :: 4 - Beta
Classifier: Intended Audience :: Education
Classifier: Programming Language :: Python :: 3
Classifier: Programming Language :: Python :: 3 :: Only
Classifier: License :: OSI Approved :: MIT License
Classifier: Operating System :: OS Independent
Classifier: Topic :: Internet :: WWW/HTTP
Classifier: Topic :: Multimedia :: Video
Requires-Python: >=3.5
Requires-Dist: requests
Requires-Dist: python-dateutil
